keble_email/__init__.py
keble_email/async_imap.py
keble_email/async_smtp.py
keble_email/imap.py
keble_email/schemas.py
keble_email-2.0.0.dist-info/LICENSE
keble_email-2.0.0.dist-info/METADATA
keble_email-2.0.0.dist-info/WHEEL
keble_email-2.0.0.dist-info/RECORD
