Metadata-Version: 2.1
Name: keble-email
Version: 2.0.0
Summary: 
Author: zhenhao-ma
Author-email: bob0103779@gmail.com
Requires-Python: >=3.10,<4.0
Classifier: Programming Language :: Python :: 3
Classifier: Programming Language :: Python :: 3.10
Classifier: Programming Language :: Python :: 3.11
Classifier: Programming Language :: Python :: 3.12
Requires-Dist: aioimaplib (>=2,<3)
Requires-Dist: aiosmtplib (>=4,<5)
Requires-Dist: emails (>=0,<1)
Requires-Dist: imap_tools (>=1,<2)
Requires-Dist: jinja2 (>=3,<4)
Requires-Dist: keble-helpers (>=1.0.2,<2)
Requires-Dist: mjml (>=0,<1)
Requires-Dist: pydantic (>=2,<3)
